topsis_Vinay_101803108/__init__.py
topsis_Vinay_101803108-0.0.1.dist-info/METADATA
topsis_Vinay_101803108-0.0.1.dist-info/WHEEL
topsis_Vinay_101803108-0.0.1.dist-info/licence.txt
topsis_Vinay_101803108-0.0.1.dist-info/top_level.txt
topsis_Vinay_101803108-0.0.1.dist-info/RECORD
