Metadata-Version: 2.1
Name: topsis-Vinay-101803108
Version: 0.0.1
Summary: TOPSIS Package to rank different models
Home-page: UNKNOWN
Author: Vinay Singh
Author-email: singh.v357@gmail.com
License: UNKNOWN
Platform: UNKNOWN
Classifier: Programming Language :: Python :: 3
Classifier: License :: OSI Approved :: MIT License
Classifier: Operating System :: OS Independent
